oshino_tcp/__init__.py
oshino_tcp/agent.py
oshino_tcp/version.py
oshino_tcp-0.1.1.dist-info/DESCRIPTION.rst
oshino_tcp-0.1.1.dist-info/METADATA
oshino_tcp-0.1.1.dist-info/RECORD
oshino_tcp-0.1.1.dist-info/WHEEL
oshino_tcp-0.1.1.dist-info/metadata.json
oshino_tcp-0.1.1.dist-info/top_level.txt
