Metadata-Version: 2.0
Name: oshino-tcp
Version: 0.1.1
Summary: TCP metrics receiver
Home-page: UNKNOWN
Author: Šarūnas Navickas
Author-email: zaibacu@gmail.com
License: UNKNOWN
Platform: UNKNOWN
Requires-Dist: oshino
